setup.cfg
setup.py
couchdb_python_curl.egg-info/PKG-INFO
couchdb_python_curl.egg-info/SOURCES.txt
couchdb_python_curl.egg-info/dependency_links.txt
couchdb_python_curl.egg-info/entry_points.txt
couchdb_python_curl.egg-info/top_level.txt
couchdbcurl/__init__.py
couchdbcurl/changes.py
couchdbcurl/client.py
couchdbcurl/dbcompact.py
couchdbcurl/design.py
couchdbcurl/multipart.py
couchdbcurl/pinger.py
couchdbcurl/schema.py
couchdbcurl/view.py
couchdbcurl/tests/__init__.py
couchdbcurl/tests/client.py
couchdbcurl/tests/couch_tests.py
couchdbcurl/tests/design.py
couchdbcurl/tests/multipart.py
couchdbcurl/tests/schema.py
couchdbcurl/tests/view.py
couchdbcurl/tools/__init__.py
couchdbcurl/tools/dump.py
couchdbcurl/tools/load.py
couchdbcurl/tools/replication_helper.py
couchdbcurl/tools/replication_helper_test.py
doc/Makefile
doc/client.rst
doc/conf.py
doc/index.rst
doc/pinger.rst