Metadata-Version: 1.1
Name: couchdb-python-curl
Version: 1.1.5
Summary: CouchDB-python wrapper (using cURL library)
Home-page: http://code.google.com/p/couchdb-python-curl/
Author: Alexey Loshkarev
Author-email: elf2001@gmail.com
License: GPL
Platform: UNKNOWN
Classifier: Development Status :: 5 - Production/Stable
Classifier: Intended Audience :: Developers
Classifier: License :: OSI Approved :: GNU General Public License (GPL)
Classifier: Natural Language :: English
Classifier: Programming Language :: Python
Classifier: Topic :: Software Development :: Libraries :: Python Modules
Classifier: Topic :: Database :: Front-Ends
